README.md
setup.py
objtree/__init__.py
objtree/cli.py
objtree.egg-info/PKG-INFO
objtree.egg-info/SOURCES.txt
objtree.egg-info/dependency_links.txt
objtree.egg-info/entry_points.txt
objtree.egg-info/requires.txt
objtree.egg-info/top_level.txt
objtree/../_agent.js
objtree/utils/__init__.py
objtree/utils/hooker.py