Metadata-Version: 1.0
Name: objtree
Version: 0.5.2
Summary: tree but for Objective-C messages
Home-page: https://github.com/hot3eed/objtree
Author: hot3eed
Author-email: hot3eed@gmail.com
License: Apache License 2.0
Keywords: dynamic-instrumentation ios macos frida debugger
Platform: UNKNOWN
